GISIC/__init__.py
GISIC/norm_functions.py
GISIC/normalize.py
GISIC/segment.py
GISIC/spectrum.py
GISIC-1.393.dist-info/LICENSE
GISIC-1.393.dist-info/METADATA
GISIC-1.393.dist-info/WHEEL
GISIC-1.393.dist-info/top_level.txt
GISIC-1.393.dist-info/RECORD
