Metadata-Version: 2.1
Name: GISIC
Version: 1.393
Summary: Gaussian Inflection Spline Interpolation Continuum
Home-page: UNKNOWN
Author: Devin D. Whitten
Author-email: dwhitten@nd.edu
License: ND
Platform: UNKNOWN
